.gitignore
CONTRIBUTORS.rst
MANIFEST.in
README.rst
TODO.rst
setup.cfg
setup.py
docs/CHANGES.rst
docs/INSTALL.txt
docs/LICENSE.GPL
docs/LICENSE.txt
src/slc/__init__.py
src/slc.linguatools.egg-info/PKG-INFO
src/slc.linguatools.egg-info/SOURCES.txt
src/slc.linguatools.egg-info/dependency_links.txt
src/slc.linguatools.egg-info/entry_points.txt
src/slc.linguatools.egg-info/namespace_packages.txt
src/slc.linguatools.egg-info/not-zip-safe
src/slc.linguatools.egg-info/requires.txt
src/slc.linguatools.egg-info/top_level.txt
src/slc/linguatools/__init__.py
src/slc/linguatools/configure.zcml
src/slc/linguatools/interfaces.py
src/slc/linguatools/patch_tinymce_breadcrumbs.py
src/slc/linguatools/testing.py
src/slc/linguatools/utils.py
src/slc/linguatools/browser/__init__.py
src/slc/linguatools/browser/compare.pt
src/slc/linguatools/browser/compare.py
src/slc/linguatools/browser/configure.zcml
src/slc/linguatools/browser/forms.py
src/slc/linguatools/browser/interfaces.py
src/slc/linguatools/browser/layout.py
src/slc/linguatools/browser/linguatools.pt
src/slc/linguatools/browser/linguatools.py
src/slc/linguatools/browser/linguatools_view.py
src/slc/linguatools/browser/vocabularies.py
src/slc/linguatools/browser/templates/form.pt
src/slc/linguatools/browser/templates/layout.pt
src/slc/linguatools/profiles/default/actions.xml
src/slc/linguatools/profiles/default/browserlayer.xml
src/slc/linguatools/profiles/default/cssregistry.xml
src/slc/linguatools/profiles/default/jsregistry.xml
src/slc/linguatools/profiles/default/metadata.xml
src/slc/linguatools/static/arrow-down.png
src/slc/linguatools/static/arrow.png
src/slc/linguatools/static/linguatools.css
src/slc/linguatools/static/linguatools.js
src/slc/linguatools/tests/__init__.py
src/slc/linguatools/tests/base.py
src/slc/linguatools/tests/lttest.txt
src/slc/linguatools/tests/test_functional.py