Metadata-Version: 1.1
Name: slc.linguatools
Version: 1.4.4
Summary: A set of tools that simplify handling multilingual content in Plone based on LinguaPlone
Home-page: http://pypi.python.org/pypi/slc.linguatools/
Author: Syslab.com GmbH
Author-email: thomas@syslab.com
License: GPL
Keywords: linguatools internationalization linguaplone
Platform: UNKNOWN
Classifier: Framework :: Plone
Classifier: Framework :: Plone :: 3.3
Classifier: Framework :: Plone :: 4.0
Classifier: Framework :: Plone :: 4.1
Classifier: Framework :: Plone :: 4.2
Classifier: Programming Language :: Python
Classifier: Topic :: Software Development :: Libraries :: Python Modules
Classifier: License :: OSI Approved :: GNU General Public License (GPL)
Classifier: License :: OSI Approved :: European Union Public Licence 1.1 (EUPL 1.1)
